boring_catalog/__init__.py
boring_catalog/catalog.py
boring_catalog/lock.py
boring_catalog/py.typed
boring_catalog-0.1.0.dist-info/METADATA
boring_catalog-0.1.0.dist-info/WHEEL
boring_catalog-0.1.0.dist-info/RECORD
