Metadata-Version: 2.4
Name: boring-catalog
Version: 0.1.0
Summary: A DuckDB-based Iceberg catalog implementation
Author-email: huraultj <julien.hurault@sumeo.io>
Requires-Python: >=3.10
Requires-Dist: duckdb>=0.9.0
Requires-Dist: pyiceberg>=0.6.0
Requires-Dist: s3fs>=2023.12.0
